csgmsh/__init__.py
csgmsh/field.py
csgmsh/mesh.py
csgmsh/shape.py
csgmsh/.ruff_cache/.gitignore
csgmsh/.ruff_cache/CACHEDIR.TAG
csgmsh/.ruff_cache/0.12.3/7553219835490112377
csgmsh-0.3.1.dist-info/licenses/LICENSE
csgmsh-0.3.1.dist-info/WHEEL
csgmsh-0.3.1.dist-info/METADATA
csgmsh-0.3.1.dist-info/RECORD
