Metadata-Version: 2.4
Name: csgmsh
Version: 0.3.1
Summary: Constructive Solid Geometry helper for Gmsh
Author-email: Evalf <info@evalf.com>
Requires-Python: >=3.9
Classifier: License :: OSI Approved :: MIT License
License-File: LICENSE
Requires-Dist: gmsh >=4,<5
Requires-Dist: treelog >=1,<2
Requires-Dist: nutils >=9,<10 ; extra == "test"
Requires-Dist: meshio >=5,<6 ; extra == "test"
Provides-Extra: test
